rbt/__debug__.py
rbt/__init__.py
rbt/__pycache__/__init__.cpython-37.pyc
rbt-1.0.0.dist-info/LICENSE
rbt-1.0.0.dist-info/METADATA
rbt-1.0.0.dist-info/WHEEL
rbt-1.0.0.dist-info/top_level.txt
rbt-1.0.0.dist-info/RECORD
