Metadata-Version: 2.1
Name: rbt
Version: 1.0.0
Summary: This is a rbt.
Home-page: https://github.com/atpuxiner/rbt
Author: axiner
Author-email: atpuxiner@163.com
License: MIT
Platform: any
Classifier: License :: OSI Approved :: MIT License
Classifier: Operating System :: OS Independent
Classifier: Programming Language :: Python :: 3
Requires-Python: >=3.8
License-File: LICENSE
